permutations/__init__.py
permutations/email_permuter.py
email_permutations-0.6.0.dist-info/LICENCE
email_permutations-0.6.0.dist-info/METADATA
email_permutations-0.6.0.dist-info/WHEEL
email_permutations-0.6.0.dist-info/top_level.txt
email_permutations-0.6.0.dist-info/RECORD
