Metadata-Version: 2.1
Name: email-permutations
Version: 0.6.0
Summary: To Find All Possible Permtations & Combinations for a given first name and last name
Home-page: https://github.com/devildani/email_permutations
Author: Pratik Dani
Author-email: danipratik91@gmail.com
License: UNKNOWN
Platform: UNKNOWN
Classifier: Programming Language :: Python :: 3
Classifier: License :: OSI Approved :: MIT License
Classifier: Operating System :: OS Independent
Requires-Python: >=3.6
